<?xml version="1.0" encoding="UTF-8"?>
<java version="1.8.0_92" class="java.beans.XMLDecoder">
 <object class="automat.mainlib.Automat">
  <void property="herstellerList">
   <object class="java.util.ArrayList">
    <void method="add">
     <object class="automat.mainlib.hersteller.HerstellerImplementation" id="HerstellerImplementation0">
      <void property="name">
       <string>alex</string>
      </void>
     </object>
    </void>
    <void method="add">
     <object class="automat.mainlib.hersteller.HerstellerImplementation">
      <void property="name">
       <string>donna</string>
      </void>
     </object>
    </void>
   </object>
  </void>
  <void property="message">
   <string>Obsttorte</string>
  </void>
  <void property="name">
   <string>kuchen automat</string>
  </void>
  <void property="platzImAutomat">
   <int>4</int>
  </void>
  <void property="storage">
   <object class="java.util.ArrayList">
    <void method="add">
     <object class="automat.mainlib.EinlagerungEntry">
      <void property="einlagerungsDatum">
       <object class="java.time.LocalDateTime" method="parse">
        <string>2020-02-05T20:12:57.875</string>
       </object>
      </void>
      <void property="kuchen">
       <object class="automat.mainlib.kuchen.KremkuchenImplementation">
        <void property="allergens">
         <object class="java.util.ArrayList" id="ArrayList0">
          <void method="add">
           <object class="java.lang.Enum" method="valueOf">
            <class>automat.mainlib.kuchen.Allergen</class>
            <string>ERDNUSS</string>
           </object>
          </void>
          <void method="add">
           <object class="java.lang.Enum" method="valueOf">
            <class>automat.mainlib.kuchen.Allergen</class>
            <string>GLUTEN</string>
           </object>
          </void>
         </object>
        </void>
        <void property="haltbarkeit">
         <object class="java.time.Duration" method="parse">
          <string>PT72H</string>
         </object>
        </void>
        <void property="hersteller">
         <object idref="HerstellerImplementation0"/>
        </void>
        <void property="kremsorte">
         <string>sahne</string>
        </void>
        <void property="naehrwert">
         <int>890</int>
        </void>
        <void property="price">
         <object class="java.math.BigDecimal">
          <string>25.5</string>
         </object>
        </void>
       </object>
      </void>
     </object>
    </void>
    <void method="add">
     <object class="automat.mainlib.EinlagerungEntry">
      <void property="einlagerungsDatum">
       <object class="java.time.LocalDateTime" method="parse">
        <string>2020-02-05T20:12:57.884</string>
       </object>
      </void>
      <void property="fachnummer">
       <int>1</int>
      </void>
      <void property="kuchen">
       <object class="automat.mainlib.kuchen.ObsttorteImplementation">
        <void property="allergens">
         <object idref="ArrayList0"/>
        </void>
        <void property="haltbarkeit">
         <object class="java.time.Duration" method="parse">
          <string>PT48H</string>
         </object>
        </void>
        <void property="hersteller">
         <object idref="HerstellerImplementation0"/>
        </void>
        <void property="kremsorte">
         <string>heidelbeeren</string>
        </void>
        <void property="naehrwert">
         <int>500</int>
        </void>
        <void property="obstsorte">
         <string>sahne</string>
        </void>
        <void property="price">
         <object class="java.math.BigDecimal">
          <string>20</string>
         </object>
        </void>
       </object>
      </void>
     </object>
    </void>
    <void method="add">
     <object class="automat.mainlib.EinlagerungEntry">
      <void property="einlagerungsDatum">
       <object class="java.time.LocalDateTime" method="parse">
        <string>2020-02-05T20:12:57.884</string>
       </object>
      </void>
      <void property="fachnummer">
       <int>2</int>
      </void>
      <void property="kuchen">
       <object class="automat.mainlib.kuchen.ObstkuchenImplementation">
        <void property="allergens">
         <object idref="ArrayList0"/>
        </void>
        <void property="haltbarkeit">
         <object class="java.time.Duration" method="parse">
          <string>PT48H</string>
         </object>
        </void>
        <void property="hersteller">
         <object idref="HerstellerImplementation0"/>
        </void>
        <void property="naehrwert">
         <int>800</int>
        </void>
        <void property="obstsorte">
         <string>Kirsche</string>
        </void>
        <void property="price">
         <object class="java.math.BigDecimal">
          <string>15</string>
         </object>
        </void>
       </object>
      </void>
     </object>
    </void>
    <void method="add">
     <object class="automat.mainlib.EinlagerungEntry">
      <void property="einlagerungsDatum">
       <object class="java.time.LocalDateTime" method="parse">
        <string>2020-02-05T20:12:57.884</string>
       </object>
      </void>
      <void property="fachnummer">
       <int>3</int>
      </void>
      <void property="kuchen">
       <object class="automat.mainlib.kuchen.ObsttorteImplementation">
        <void property="allergens">
         <object class="java.util.ArrayList">
          <void method="add">
           <object class="java.lang.Enum" method="valueOf">
            <class>automat.mainlib.kuchen.Allergen</class>
            <string>HASELNUSS</string>
           </object>
          </void>
          <void method="add">
           <object class="java.lang.Enum" method="valueOf">
            <class>automat.mainlib.kuchen.Allergen</class>
            <string>SESAMSAMEN</string>
           </object>
          </void>
         </object>
        </void>
        <void property="haltbarkeit">
         <object class="java.time.Duration" method="parse">
          <string>PT48H</string>
         </object>
        </void>
        <void property="hersteller">
         <object idref="HerstellerImplementation0"/>
        </void>
        <void property="kremsorte">
         <string>Kirsche</string>
        </void>
        <void property="naehrwert">
         <int>800</int>
        </void>
        <void property="obstsorte">
         <string>Sahne</string>
        </void>
        <void property="price">
         <object class="java.math.BigDecimal">
          <string>15</string>
         </object>
        </void>
       </object>
      </void>
     </object>
    </void>
   </object>
  </void>
 </object>
</java>
